{
	"configurations" : 
	[
		{
			"directories" : 
			[
				{
					"build" : ".",
					"hasInstallRule" : true,
					"jsonFile" : "directory-.-06859fe2a94d51f0e646.json",
					"minimumCMakeVersion" : 
					{
						"string" : "3.12"
					},
					"projectIndex" : 0,
					"source" : ".",
					"targetIndexes" : 
					[
						0,
						1,
						2,
						3
					]
				}
			],
			"name" : "",
			"projects" : 
			[
				{
					"directoryIndexes" : 
					[
						0
					],
					"name" : "armor_tracker",
					"targetIndexes" : 
					[
						0,
						1,
						2,
						3
					]
				}
			],
			"targets" : 
			[
				{
					"directoryIndex" : 0,
					"id" : "armor_tracker::@6890427a1f51a3e7e1df",
					"jsonFile" : "target-armor_tracker-70bc042124fd46b8b236.json",
					"name" : "armor_tracker",
					"projectIndex" : 0
				},
				{
					"directoryIndex" : 0,
					"id" : "armor_tracker_node::@6890427a1f51a3e7e1df",
					"jsonFile" : "target-armor_tracker_node-32e860dd5b6014c423b7.json",
					"name" : "armor_tracker_node",
					"projectIndex" : 0
				},
				{
					"directoryIndex" : 0,
					"id" : "armor_tracker_uninstall::@6890427a1f51a3e7e1df",
					"jsonFile" : "target-armor_tracker_uninstall-4a446bccf918e896f0bd.json",
					"name" : "armor_tracker_uninstall",
					"projectIndex" : 0
				},
				{
					"directoryIndex" : 0,
					"id" : "uninstall::@6890427a1f51a3e7e1df",
					"jsonFile" : "target-uninstall-8fff344813ad15708f62.json",
					"name" : "uninstall",
					"projectIndex" : 0
				}
			]
		}
	],
	"kind" : "codemodel",
	"paths" : 
	{
		"build" : "/home/coffee/rv_autokal/build/armor_tracker",
		"source" : "/home/coffee/rv_autokal/src/rm_auto_aim/armor_tracker"
	},
	"version" : 
	{
		"major" : 2,
		"minor" : 3
	}
}
